tosheets/__init__.py
tosheets/client.json
tosheets/tosheets.py
tosheets-0.4.2.dist-info/LICENSE
tosheets-0.4.2.dist-info/METADATA
tosheets-0.4.2.dist-info/WHEEL
tosheets-0.4.2.dist-info/entry_points.txt
tosheets-0.4.2.dist-info/top_level.txt
tosheets-0.4.2.dist-info/RECORD
