Metadata-Version: 2.1
Name: tosheets
Version: 0.4.2
Summary: Cmd utility that send stdin to google sheets
Home-page: https://github.com/kren1/tosheets
Author: Timotej Kapus
Author-email: kren1@users.noreply.github.com
License: MIT
Keywords: utility sheets command line
Platform: UNKNOWN
Classifier: Intended Audience :: Developers
Classifier: Natural Language :: English
Classifier: Operating System :: OS Independent
Classifier: Programming Language :: Python :: 3
Requires-Dist: docopt
Requires-Dist: oauth2client
Requires-Dist: google-api-python-client
